weight2cpp/__init__.py
weight2cpp/weight2cpp.py
weight2cpp-0.11.dist-info/METADATA
weight2cpp-0.11.dist-info/WHEEL
weight2cpp-0.11.dist-info/top_level.txt
weight2cpp-0.11.dist-info/RECORD
